VerilogCodes/ripple.v
 
 module ripple_carry_counter (q, clk, reset);
   output [3:0] q;
   input clk, reset;
   T_FF tff0(q[0], clk, reset);
   T_FF tff1(q[1], q[0], reset);
   T_FF tff2(q[2], q[1], reset);
   T_FF tf30(q[3], q[2], reset);
 
 endmodule

VerilogCodes/stimulus_block.v
 
 

 
 
 
 module T_FF(q, clk, reset);
 
   output q;
   input clk, reset;
   wire d;
   
   D_FF dff0(q, d, clk, reset);
   not n1(d,q);

endmodule

module D_FF(q, d, clk, reset);

   
  output q;
  input d, clk, reset;
  reg q;
  always @(posedge reset or negedge clk)
  if (reset)
     q = 1'b0;
  else
     q = d;
endmodule
 
 
module stimulus;
reg clk;
reg reset;
wire[3:0] q;

//instantiate the design block

ripple_carry_counter r1 (q,clk, reset);

//control the clk signal that drives the design block cycle time = 10
initial 
   clk = 'b0; // set clk to 0
always
   #5 clk = ~clk; // toggole clk every 5 times units
   
   
   // Control the reset signal that drives the design block
   //reset is asserted from 0 to 20 and from 200 to 220.

initial
begin

    $dumpfile("stimulus_block.vcd");
    $dumpvars(0,stimulus);   
    reset = 1'b1;
    #15 reset = 1'b0;
    #180 reset = 1'b1;
    #10 reset = 1'b0;
    #20 $finish; //terminate the simulation
 end
 
 //Monitor the outputs
 
 initial
     
     $monitor($time, "output q = %d", q);
     
 endmodule

VerilogCodes/stimulus_block.vcd
$date
      Wed Apr 19 13:03:44 2023

$end
$version
      Veriwell 2.8.7
$end
$timescale
      1s
$end


$scope module stimulus $end
$var reg       1 !    clk  $end
$var reg       1 "    reset  $end
$var wire      4 #    q [3:0] $end

$scope module r1 $end
$var wire      1 $    reset  $end
$var wire      1 %    clk  $end
$var wire      4 &    q [3:0] $end

$scope module tf30 $end
$var wire      1 '    reset  $end
$var wire      1 (    clk  $end
$var wire      1 )    q  $end
$var wire      1 *    d  $end

$scope module dff0 $end
$var wire      1 +    reset  $end
$var wire      1 ,    clk  $end
$var wire      1 -    d  $end
$var reg       1 .    q  $end
$upscope $end

$upscope $end


$scope module tff2 $end
$var wire      1 /    reset  $end
$var wire      1 0    clk  $end
$var wire      1 1    q  $end
$var wire      1 2    d  $end

$scope module dff0 $end
$var wire      1 3    reset  $end
$var wire      1 4    clk  $end
$var wire      1 5    d  $end
$var reg       1 6    q  $end
$upscope $end

$upscope $end


$scope module tff1 $end
$var wire      1 7    reset  $end
$var wire      1 8    clk  $end
$var wire      1 9    q  $end
$var wire      1 :    d  $end

$scope module dff0 $end
$var wire      1 ;    reset  $end
$var wire      1 <    clk  $end
$var wire      1 =    d  $end
$var reg       1 >    q  $end
$upscope $end

$upscope $end


$scope module tff0 $end
$var wire      1 ?    reset  $end
$var wire      1 @    clk  $end
$var wire      1 A    q  $end
$var wire      1 B    d  $end

$scope module dff0 $end
$var wire      1 C    reset  $end
$var wire      1 D    clk  $end
$var wire      1 E    d  $end
$var reg       1 F    q  $end
$upscope $end

$upscope $end

$upscope $end

$upscope $end

$enddefinitions      $end
#0
$dumpvars
0F
1E
0D
1C
1B
0A
0@
1?
0>
1=
0<
1;
1:
09
08
17
06
15
04
13
12
01
00
1/
0.
1-
0,
1+
1*
0)
0(
1'
b0 &
0%
1$
b0 #
1"
0!
$end
#5
1!
1D
1@
1%
#10
0!
0D
0@
0%
#15
0"
1!
0C
0?
0;
07
03
0/
0+
0'
0$
1D
1@
1%
#20
0!
0D
0@
0%
1F
1A
b1 &
b1 #
0E
0B
1<
18
#25
1!
1D
1@
1%
#30
0!
0D
0@
0%
0F
0A
b0 &
b0 #
1E
1B
0<
08
1>
19
b10 &
b10 #
0=
0:
14
10
#35
1!
1D
1@
1%
#40
0!
0D
0@
0%
1F
1A
b11 &
b11 #
0E
0B
1<
18
#45
1!
1D
1@
1%
#50
0!
0D
0@
0%
0F
0A
b10 &
b10 #
1E
1B
0<
08
0>
09
b0 &
b0 #
1=
1:
04
00
16
11
b100 &
b100 #
05
02
1,
1(
#55
1!
1D
1@
1%
#60
0!
0D
0@
0%
1F
1A
b101 &
b101 #
0E
0B
1<
18
#65
1!
1D
1@
1%
#70
0!
0D
0@
0%
0F
0A
b100 &
b100 #
1E
1B
0<
08
1>
19
b110 &
b110 #
0=
0:
14
10
#75
1!
1D
1@
1%
#80
0!
0D
0@
0%
1F
1A
b111 &
b111 #
0E
0B
1<
18
#85
1!
1D
1@
1%
#90
0!
0D
0@
0%
0F
0A
b110 &
b110 #
1E
1B
0<
08
0>
09
b100 &
b100 #
1=
1:
04
00
06
01
b0 &
b0 #
15
12
0,
0(
1.
1)
b1000 &
b1000 #
0-
0*
#95
1!
1D
1@
1%
#100
0!
0D
0@
0%
1F
1A
b1001 &
b1001 #
0E
0B
1<
18
#105
1!
1D
1@
1%
#110
0!
0D
0@
0%
0F
0A
b1000 &
b1000 #
1E
1B
0<
08
1>
19
b1010 &
b1010 #
0=
0:
14
10
#115
1!
1D
1@
1%
#120
0!
0D
0@
0%
1F
1A
b1011 &
b1011 #
0E
0B
1<
18
#125
1!
1D
1@
1%
#130
0!
0D
0@
0%
0F
0A
b1010 &
b1010 #
1E
1B
0<
08
0>
09
b1000 &
b1000 #
1=
1:
04
00
16
11
b1100 &
b1100 #
05
02
1,
1(
#135
1!
1D
1@
1%
#140
0!
0D
0@
0%
1F
1A
b1101 &
b1101 #
0E
0B
1<
18
#145
1!
1D
1@
1%
#150
0!
0D
0@
0%
0F
0A
b1100 &
b1100 #
1E
1B
0<
08
1>
19
b1110 &
b1110 #
0=
0:
14
10
#155
1!
1D
1@
1%
#160
0!
0D
0@
0%
1F
1A
b1111 &
b1111 #
0E
0B
1<
18
#165
1!
1D
1@
1%
#170
0!
0D
0@
0%
0F
0A
b1110 &
b1110 #
1E
1B
0<
08
0>
09
b1100 &
b1100 #
1=
1:
04
00
06
01
b1000 &
b1000 #
15
12
0,
0(
0.
0)
b0 &
b0 #
1-
1*
#175
1!
1D
1@
1%
#180
0!
0D
0@
0%
1F
1A
b1 &
b1 #
0E
0B
1<
18
#185
1!
1D
1@
1%
#190
0!
0D
0@
0%
0F
0A
b0 &
b0 #
1E
1B
0<
08
1>
19
b10 &
b10 #
0=
0:
14
10
#195
1"
1!
1C
1?
1;
17
13
1/
1+
1'
1$
1D
1@
1%
0>
09
b0 &
b0 #
1=
1:
04
00
#200
0!
0D
0@
0%
#205
0"
1!
0C
0?
0;
07
03
0/
0+
0'
0$
1D
1@
1%
#210
0!
0D
0@
0%
1F
1A
b1 &
b1 #
0E
0B
1<
18
#215
1!
1D
1@
1%
#220
0!
0D
0@
0%
0F
0A
b0 &
b0 #
1E
1B
0<
08
1>
19
b10 &
b10 #
0=
0:
14
10
